pyvalkey/__init__.py
pyvalkey/__main__.py
pyvalkey/commands/__init__.py
pyvalkey/commands/acls.py
pyvalkey/commands/admins.py
pyvalkey/commands/bits.py
pyvalkey/commands/clients.py
pyvalkey/commands/configs.py
pyvalkey/commands/context.py
pyvalkey/commands/core.py
pyvalkey/commands/creators.py
pyvalkey/commands/databases.py
pyvalkey/commands/dependencies.py
pyvalkey/commands/geo_commands.py
pyvalkey/commands/hash_maps.py
pyvalkey/commands/informations.py
pyvalkey/commands/keyspace_commands.py
pyvalkey/commands/lists.py
pyvalkey/commands/parameters.py
pyvalkey/commands/parsers.py
pyvalkey/commands/router.py
pyvalkey/commands/servers.py
pyvalkey/commands/sets.py
pyvalkey/commands/sorted_sets.py
pyvalkey/commands/utils.py
pyvalkey/database_objects/__init__.py
pyvalkey/database_objects/acl.py
pyvalkey/database_objects/clients.py
pyvalkey/database_objects/configurations.py
pyvalkey/database_objects/databases.py
pyvalkey/database_objects/errors.py
pyvalkey/database_objects/information.py
pyvalkey/database_objects/utils.py
pyvalkey/resp.py
pyvalkey/server.py
pyvalkey-0.0.5.dist-info/LICENSE
pyvalkey-0.0.5.dist-info/METADATA
pyvalkey-0.0.5.dist-info/WHEEL
pyvalkey-0.0.5.dist-info/RECORD
