Metadata-Version: 2.1
Name: pyvalkey
Version: 0.0.5
Summary: pyvalkey: Python implemented Valkey server
License: MIT
Author: Netanel Revah
Author-email: netanelrevah@outlook.com
Requires-Python: >=3.11,<4.0
Classifier: License :: OSI Approved :: MIT License
Classifier: Programming Language :: Python :: 3
Classifier: Programming Language :: Python :: 3.11
Classifier: Programming Language :: Python :: 3.12
Requires-Dist: sortedcontainers (>=2.4.0,<3.0.0)
Requires-Dist: typer (>=0.12,<0.13)
Requires-Dist: typing-extensions (>=4.8.0,<5.0.0)
